Workbook

Sheet 転記
B3: ↓黄色セルはすべてに記入をお願いいたします。
A4: 項目 | B4: 記入欄 | C4: 補足
A6: GビズIDプライム
A8: 企業名
A10: 企業名（フリガナ）
A12: 店舗事業所数
A14: 事業者URL
A16: 主な事業内容
A17: 他社に負けない貴社の「強み」は何ですか？
A18: 現在「時間がかかっている業務」は何ですか？
A19: その業務に「月間何時間」ほど費やしていますか？
A20: 導入するツールのどの機能を使って、どう楽にしたいですか？
A21: 導入後、事務作業時間は「何％（あるいは何時間）」削減できそうですか？
A22: 作業が楽になり「浮いた時間」で、どのような価値を生む業務を行いますか？
... A46: 従業員数：その他
A48: 過去にサービス等生産性向上IT導入支援事業の補助金の交付を受けている | C48: ①有 ②無
A49: ⇨「有」の場合、下記についてお教えください
A50: 申請年度
A51: 申請枠
A52: 申請回
A55: 女性活躍推進法に基づく一般事業主行動計画
A56: えるぼし認定取得状況 | C56: ① えるぼし認定 ② プラチナえるぼし認定 ③ 認定なし
A58: 次世代法に基づく一般事業主行動計画
A59: くるみん認定取得状況 | C59: ① くるみん認定 ② プラチナくるみん認定 ③ トライくるみん認定 ④ 認定なし
A61: SECURITY ACTION自己宣言ID
A63: ◼️前期決算終了時の状況をお教えください
A64: 従業員数：正規雇用
A65: 従業員数：契約社員
A66: 従業員数：パートアルバイト
A67: 年間の平均労働時間
A69: 【賃上げ計画について】
A70: 事業所内最低賃金時給
A72: 賃金引上げ計画を、従業員へ表明しましたか？ | C72: 賃上げ表明を行わない場合は、弊社までご相談ください。
A74: 賃金引上げ計画
A75: ◼️表明を行った従業員名
A76: 従業員代表者
A77: 給与担当者
A78: 事業所内最低賃金者
A80: 【インボイス制度対応状況について】
A81: インボイス制度（適格請求書発行時業者）への登録はお済みでしょうか？
A82: 「未登録」の場合、下記についてお答えください
A83: 交付申請日から実績報告日までにインボイス登録を行いますか？
A85: 【賃金状況について】
A86: 指定する一定期間（令和6年10月〜令和7年9月）において当該期間における地域別最低賃金以上～令和7年度改定の地域別最低賃金未満で雇用している従業員数が全従業員の30%以上である月が3ヶ月以上ありますか？
A87: 交付申請の直近月における事業場内最低賃金が令和7年7月の事業場内最低賃金+63円以上となっていますか？

Sheet 申請内容
B2: ◼️シート作成
B3: ◼️ダブルチェック
B5: GビズIDプライム
B6: ='転記'!B6
B8: 申請時添付資料 | E8: 資料例
B9: FALSE | C9: 履歴事項全部証明書の写し | D9: ・申請日の3ヶ月以内の取得 ・法務局で取得している | E9: 履歴事項全部証明書.pdf
B10: FALSE | C10: 法人税の納税証明書 （その１もしくはその２） | D10: ・法人税である ・「その１」もしくは「その２」である（※その３は不可） ・納税額 0円でもOK ・発行元：税務署 | E10: 納税証明書（法人）.pdf
B11: FALSE | C11: 「IT戦略ナビwith」の実施結果/PDF | D11: ・gBizIDプライム（メールアドレス）が確認できる ・資料の枚数が揃っている | E11: IT戦略ナビwith
B13: フォーマット作成者 チェック項目 | E13: 資料例
B14: FALSE | C14: 過去採択者検索 | D14: 補助金採択事業者 | E14: 補助金採択事業者（https://mirasapo-connect.go.jp/chusho-subsidies）にて確認 ※ 2022以前はExcelで確認 採択事業者チェックシート.xlsx
C15: ⇨ありの場合 過去ツール内容をこちらに記載
B16: FALSE | C16: 「成長加速マッチングサービス」の実施/画面スクショ | D16: ・登録されている挑戦課題のステータスが「掲載中」となっている | E16: 成長加速マッチングサービス
B17: FALSE | C17: 「省力化ナビ」
B18: FALSE | C18: 決算書2期分（製造原価報告書） | D18: ・製造業をされてる場合は「製造原価報告書」も必要 →無い場合はお客様へ確認(※子会社で製造や外注等で無い場合もあり) ・直近分の貸借対照表と損益計算書は申請時に提出
B19: FALSE | C19: 申請フォーマット 追記 | D19: ➀下記社内用申請ＦＭをコピーし、タイトル「お客様名_申請フォーマット」にする ②お客様が記入した申請ＦＭをこのスプレッドシートの「転記」へコピぺする ③社内用申請ＦＭに従い、内容をチェック・追記する（オレンジの項目） ④内容不備等の要確認の箇所はセルを赤にし、伝言事項に詳細を記入
B20: FALSE | C20: 申請金額の確認 | D20: 見積書をもとに『申請金額』シートへ記入 ※見積書は各案件管理シートのGoogleフォームより確認
B21: FALSE | C21: 申請フォーマット 最終確認 | D21: 作成者自身でWチェック ⇨箕川さん作成のWチェックシート
B23: ダブルチェック ※フォーマット作成者以外
B24: FALSE | C24: 資料確認
B25: FALSE | C25: 申請フォーマットの内容確認→案件管理表更新
B30: 『注意喚起』の動画をクリックし、「次へ」
B32: 申請類型選択
B34: 項目 | C34: 記入欄 | D34: 作成・確認方法 | E34: 伝言事項
B35: 申請類型選択 | C35: □ インボイス対応類型（50万円以下） ■ インボイス対応類型（50万円超） □ 電子取引類型
B37: 『 次へ 』 | C37: をクリック
B39: 基本情報入力
B41: 法人番号 | C41: 法人の場合、ログイン画面に表示 | E41: 『情報取得』をクリックすると、事業者名、本社所在地の郵便番号・都道府県・市区町村が自動的に反映
B42: 事業者名 | C42: ='転記'!B8 | D42: 『履歴事項全部証明書』にて確認 下線が入った内容は過去の情報の為不可
B43: 事業者名フリガナ | C43: ='転記'!B10
B44: 本店所在地 郵便番号 | C44: =IFERROR(__xludf.DUMMYFUNCTION("IMPORTXML(""https://api.excelapi.org/post/zipcode?address=""&ENCODEURL(C45),""."")"),"#REF!") | D44: ※住所から郵便番号自動検索（数字のみ、ハイフンなし） 法人番号の情報取得より入力されるが、確認のため入力
B45: 本店所在地 住所 | D45: 『履歴事項全部証明書』より記入 下線が入った内容は過去の情報の為不可
B46: 業種コード （数字４桁） | D46: 複数の事業を行っている場合 ⇨「履歴事項全部証明書の目的の1番上の事業」もしくは「売上の高い事業」 →「申請ツール」により整合制のある事業を選択する（中小企業定義に関係するので売上の立っている事業以外を選択する場合は相談） 日本標準産業分類(令和５年[2023年]７月改定) 細分類コードを入力（数字４桁）
B47: 業種_大分類/中分類/小分類/細分類 | D47: ※申請サポート時にお客様に確認するため、分類をメモしておく
B48: 設立年月日 ※ダブルクリックでカレンダー表示 | D48: 『履歴事項全部証明書』にて確認 ※申請時はカレンダーで選択
B49: 資本金 | D49: 『履歴事項全部証明書』より記入 半角数字のみ、カンマ無し
B50: 店舗事業所数 | C50: ='転記'!B12
B51: 事業者URL | C51: ='転記'!B14 | D51: 公式サイトのURL
B52: 主な事業内容 | C52: ='転記'!B16
B53: 他社に負けない貴社の「強み」は何ですか？ | C53: ='転記'!B17
B54: 現在「時間がかかっている業務」は何ですか？ | C54: ='転記'!B18
B55: その業務に「月間何時間」ほど費やしていますか？ | C55: ='転記'!B19
B56: 導入するツールのどの機能を使って、どう楽にしたいですか？ | C56: ='転記'!B20
B57: 導入後、事務作業時間は「何％（あるいは何時間）」削減できそうですか？ | C57: ='転記'!B21
B58: 作業が楽になり「浮いた時間」で、どのような価値を生む業務を行いますか？ | C58: ='転記'!B22
B59: 3年後の「売上目標」を教えてください | C59: ='転記'!B23
B60: どのような属性の取引先が多いですか？ | C60: ='転記'!B24
B61: ツール名
B62: プロンプト | C62: ="以下のヒアリング情報を基に、デジタル化・AI導入補助金（インボイス枠）の申請に必要な「事業内容・実施計画」の文章を作成してください。"&CHAR(10)& "【ヒアリング情報】"&CHAR(10)& "事業内容： "&C52&CHAR(10)& "自社の強み： "&C53&CHAR(10)& "現在の課題（弱み）： "&C54&"（"&C55&"費やしている）"&CHAR(10)& "導入ツールと改善点： "&C61&" "&C56&CHAR(10)& "空いた時間で行う業務： "&C58&CHAR(10)& "具体的な数値目標："&CHAR(10)& "業務削減率： "&C57&CHAR(10)& "3年後の売上目標： "&C59&CHAR(10)& "賃上げ計画： 年率3.0%以上の賃上げを実施"&CHAR(10)& "主な取引先： "&C60&CHAR(10)&CHAR(10)& "【構成指示：以下の流れで記述してください】"&CHAR(10)& "事業概要と強み： 自社の立ち位置と競争優位性を簡潔に。"&CHAR(10)& "直面している課題とIT導入の必要性： インボイス制度への対応遅れや、具体的な業務のボトルネックを「弱み」として提示。"&CHAR(10)& "IT導入による具体的改善： ツールによってどの業務がどう変わるか。"&CHAR(10)& "投資効果と将来展望： 削減された時間（％）をどう活用し、3年後の売上拡大と賃上げ3.0%をどう達成するか、因果関係を明確にする。"&CHAR(10)&CHAR(10)& "【トーン＆マナー】"&CHAR(10)& "専門用語を避けつつ、論理的で意欲的なビジネス文章。"&CHAR(10)& "補助金の趣旨（生産性向上）に合致した表現を使用すること。"&CHAR(10)&CHAR(10)& "【出力条件】"&CHAR(10)& "・Pythonツールを使用して正確な文字数をカウントし、必ず「250文字以上、255文字以内」の範囲内に収めてください。"&CHAR(10)& "・回答には「作成した文章のみ」を出力してください。"&CHAR(10)& "・文字数の数値や「〇〇文字です」といったカウント結果、および挨拶などは一切記載しないでください。"&CHAR(10)& "・250文字に満たない、または255文字を超える場合は、範囲内に収まるまで内部でセルフチェックと調整を繰り返してください。"
B63: 事業内容（255文字以内） 自社(自己)の事業概要を説明し、今回の補助事業で導入するITツールを どのように活用するのかを具体的に記載してください。 | C63: =IFERROR(__xludf.DUMMYFUNCTION("AI(C62)"),"地域密着型のリフォーム・内装工事を主軸とする当社は、社長一貫の現場管理と迅速な対応力が強みです。しかし、インボイス制度対応を含む月40時間の事務作業がボトルネックとなり、見積遅延による失注リスクを招いています。この課題を解決するため、ITツールを導入し、現場移動中もスマホでインボイス対応の請求書作成を可能にします。これにより事務作業時間を75%（月40時間から10時間）削減します。浮いた時間を新規パートナー開拓や省エネ建材の提案営業に集中投下することで、3年後の売上目標9,500万円（118%）を達成し、"&"生産性向上と年率3.0%以上の賃上げを実現します。") | D63: ※AI Worksにて作成 参考：過去事業内容 | E63: =LEN(C63)
B64: 決算月
B65: 担当部署 | D65: 空欄可
B66: 担当者氏名 | C66: ='転記'!B28
B67: 担当者氏名フリガナ | C67: ='転記'!B30
B68: 担当者メールアドレス | C68: ='転記'!B32 | D68: 招待メール送付先 ※連絡を取り合っているアドレスでない可能性あり ※GビズIDに登録しているアドレス以外でOK ※招待後は交付結果が出るまで変更できない（申請中に変更したい場合は、再招待が必要）
B69: 担当者電話番号 | C69: ='転記'!B34 | D69: ハイフンなし
B70: 担当者携帯番号 | C70: ='転記'!B36 | D70: ハイフンなし ※今年度の本事業にて既に登録されている電話番号は使用不可
B71: 代表者・役員数 | D71: 代表者を含めた役員数 『履歴事項全部証明書』より記入 名前に下線が入った方は含めない（下線は過去の情報の為）
B72: 代表者役職
B73: 代表者氏名
B74: 代表者氏名（フリガナ）
B75: 代表電話番号 | C75: ='転記'!B26 | D75: ハイフンなし
B76: ⇩必要に応じて（7名以上の場合は追加、不要欄は削除）
B77: 役員（1）役職
B78: 役員（1）氏名
B79: 役員（1）氏名フリガナ | D79: フリガナは申請時に担当者へ確認
B80: 役員（2）役職
B81: 役員（2）氏名
B82: 役員（2）氏名フリガナ
B83: 役員（3）役職
B84: 役員（3）氏名
B85: 役員（3）氏名フリガナ
B86: 役員（4）役職
B87: 役員（4）氏名
B88: 役員（4）氏名フリガナ
B89: 役員（5）役職
B90: 役員（5）氏名
B91: 役員（5）氏名フリガナ
... B106: 役員（10）氏名フリガナ
B107: 従業員数：正規雇用 | C107: ='転記'!B38 | D107: 申請時の人数 ※実績報告時に人数が変更になった場合は修正
B108: 従業員数：契約社員 | C108: ='転記'!B40 | D108: 申請時の人数
B109: 従業員数：パートアルバイト | C109: ='転記'!B42 | D109: 申請時の人数
B110: 従業員数：派遣社員 | C110: ='転記'!B44 | D110: 申請時の人数
B111: 従業員数：その他 | C111: ='転記'!B46 | D111: 申請時の人数
B112: 過去年度交付決定 （過去に類似の補助金の交付を受けている） ※類似の補助金とは、当該年度以外の中小企業デジタル化・AI導入支援事業費補助金を指します。 | D112: 『転記』シートより、プルダウンを選択（あり/なし） ※採択日から12ヶ月未満の場合は申請不可 ※過去採択者検索
B113: 申請年度
B114: 申請枠 | C114: ='転記'!B51
B115: 申請回 | C115: ='転記'!B52
B116: えるぼし認定 | D116: 『転記』シートより、プルダウンを選択（はい/いいえ）
B117: くるみん認定 | D117: 『転記』シートより、プルダウンを選択（はい/いいえ）
B118: 「省力化ナビ」による加点について
B120: 『 次へ 』 | C120: をクリック
B122: SECURITY ACTION照合
B124: SECURITY ACTION自己宣言ID | C124: ='転記'!B61 | D124: 自己宣言ID（5から始まる11桁）であることを確認 ※2026年3月以前登録の場合は4から始まる11桁（1次公募までは使用可能）
B126: 『 次へ 』
B128: IT戦略ナビwithの実施有無の確認
B130: IT戦略ナビwithの実施有無 （加点）
B131: ファイル添付 | C131: ※添付資料のアドレスとgBizIDプライムの一致を確認 ファイル名に空白（スペース）が入っていないか確認 | E131: 資料リンクを貼る
B133: 『 次へ 』 | C133: をクリック
B135: 申請要件に関する確認
B137: 行っている事業に該当するものすべて選択 | D137: ※複数選択
...

Sheet 給与支給総額計算
A2: オレンジの項目：決算書より数値を入力してください
A3: 【財務情報について】 | D3: 【人件費】 | H3: 【従業員一人当たりのおおよその給与計算】
B4: 前事業年度 | E4: 販管費 | F4: 原価報告書 | H4: 販管費 | I4: 原価報告書
A5: 正規雇用 | B5: ='申請内容'!C143 | C5: 人 | D5: 給料手当 | J5: ←役員報酬・役員賞与など役員に関わる給与以外をコピペ
A6: 契約社員 | B6: ='申請内容'!C144 | C6: 人 | D6: 雑給
A7: パートアルバイト | B7: ='申請内容'!C145 | C7: 人 | D7: 賞与手当
A8: 役員数 | B8: ='申請内容'!C146 | C8: 人
A9: 年間の平均労働時間 | B9: ='申請内容'!C147 | C9: 時間 | D9: 旅費交通費
A10: 売上高 | C10: 円 | D10: 合計 | E10: =sum(E5:E9) | F10: =sum(F5:F9) | H10: =SUM(H5:H9)+SUM(I5:I9)
A11: 粗利益 | C11: 円 | D11: 人件費合計 | E11: =sum(E10:F10) | H11: =H10/(B5+B6+B7) | J11: ←一人当たりの年間給与(おおよそ)
A12: 営業利益 | C12: 円
A13: 経常利益 | C13: 円
A14: 減価償却費 | B14: =IF(E17=0,"",E17) | C14: 円
D15: 【減価償却費】
D16: 減価償却費
D17: 合計 | E17: =E16+F16

Sheet 給与支給総額計算 (旧)
A2: オレンジの項目：決算書より数値を入力してください
A3: 【財務情報について】 | D3: 【給与支給総額】
B4: 前事業年度 | E4: 販管費 | F4: 原価報告書
A5: 正規雇用 | B5: ='申請内容'!C134 | C5: 人 | D5: 給料手当
A6: 契約社員 | B6: ='申請内容'!C135 | C6: 人 | D6: 雑給
A7: パートアルバイト | B7: ='申請内容'!C136 | C7: 人 | D7: 賞与手当
A8: 役員数 | B8: ='申請内容'!C71 | C8: 人 | D8: 役員報酬
A9: 年間の平均労働時間 | B9: ='申請内容'!C138 | C9: 時間 | D9: 役員賞与
A10: 売上高 | C10: 円
A11: 粗利益 | C11: 円
A12: 営業利益 | C12: 円 | D12: 合計 | E12: =SUM(E5:E11) | F12: =SUM(F5:F11)
A13: 経常利益 | C13: 円 | D13: 総支給額 | E13: =SUM(E12:F12)
A14: 減価償却費 | C14: 円
A15: 減価償却費(原価報告書) | C15: 円 原価償却費合計 | D15: =IF((B14+B15)=0,"",(B14+B15)) | E15: 円
A16: 資本金 | B16: ='申請内容'!C49 | C16: 円
A17: ※ 資本金：個人事業主は「0」を入力
A18: ※ 申請金額が売上の1/5以内であるか確認
A23: 【賃上げ計画】
B24: 直近決算期の給与支給総額 | C24: 2025/4～ 2026/3 計画数値 | D24: 2026/4～ 2027/3 計画数値 | E24: 2027/4～ 2028/3 計画数値
A25: 給与支給総額 | B25: =E13 | C25: =B25*1.0155 | D25: =C25*1.0155 | E25: =D25*1.0155
A26: 増加率 （年平均成長率） | C26: =(C25-B25)/B25 | D26: =(D25-C25)/C25 | E26: =(E25-D25)/D25

Sheet 申請金額
B1: 入力しない | C1: 入力しない | D1: 商品を選択 | E1: ↓価格はサブスク1年分を記載
B2: No. | C2: 管理コード | D2: 商品名 | E2: 価格 | F2: 個数 | G2: 導入数量（箇年/回） | H2: 金額 | J2: 下限金額 | K2: 上限金額
A3: 1 | B3: =VLOOKUP(D3,'商品マスタ'!B:F,2,FALSE) | C3: =VLOOKUP(D3,'商品マスタ'!B:F,4,FALSE) | H3: =E3*F3*G3 | J3: =VLOOKUP(D3,'商品マスタ'!B:H,5,FALSE) | K3: =VLOOKUP(D3,'商品マスタ'!B:H,6,FALSE)
A4: 2 | B4: =VLOOKUP(D4,'商品マスタ'!B:F,2,FALSE) | C4: =VLOOKUP(D4,'商品マスタ'!B:F,4,FALSE) | H4: =E4*F4*G4 | J4: =VLOOKUP(D4,'商品マスタ'!B:H,5,FALSE) | K4: =VLOOKUP(D4,'商品マスタ'!B:H,6,FALSE)
A5: 3 | B5: =VLOOKUP(D5,'商品マスタ'!B:F,2,FALSE) | C5: =VLOOKUP(D5,'商品マスタ'!B:F,4,FALSE) | H5: =E5*F5*G5 | J5: =VLOOKUP(D5,'商品マスタ'!B:H,5,FALSE) | K5: =VLOOKUP(D5,'商品マスタ'!B:H,6,FALSE)
A6: 4 | B6: =VLOOKUP(D6,'商品マスタ'!B:F,2,FALSE) | C6: =VLOOKUP(D6,'商品マスタ'!B:F,4,FALSE) | H6: =E6*G6 | J6: =VLOOKUP(D6,'商品マスタ'!B:H,5,FALSE) | K6: =VLOOKUP(D6,'商品マスタ'!B:H,6,FALSE)
A7: 5 | H7: =E7*F7*G7 | I7: 売上の20％
E8: 合計金額（税抜） | H8: =SUM(H3:H7) | I8: ='給与支給総額計算 (旧)'!B10*0.2 | J8: ←合計金額が売上高の20％以内か確認
E9: 消費税 | H9: =H8*0.1
E11: 総額 | H11: =SUM(H8:H10)
E13: 補助金額 | H13: =MIN(ROUNDDOWN((H8-666667)*2/3, 0) + 500000, 3500000)
B14: 見積もりのスクショを貼る↓

Sheet 小規模事業者確認
C3: ↓コードを入力する
B4: 大分類 | C4: 業種コード（先頭2桁） | D4: 中分類 | E4: 業種区分 | F4: 従業員数
B6: =VLOOKUP(C6,'分類表'!A:G,2,FALSE) | C6: 8 | D6: =VLOOKUP(C6,'分類表'!A:G,3,FALSE) | E6: =VLOOKUP(C6,'分類表'!A:G,4,FALSE) | F6: =VLOOKUP(C6,'分類表'!A:G,5,FALSE)
C7: 例）0609の場合は06 | F7: 従業員数を確認し、上記に該当する場合は小規模事業者

Sheet 分類表
A2: 1 | B2: A 農業、林業 | C2: 農業 | D2: 支給対象外
A3: 2 | B3: A 農業、林業 | C3: 林業
A4: 3 | B4: B 漁業 | C4: 漁業
A5: 4 | B5: B 漁業 | C5: 水産養殖業
A6: 5 | B6: Ｃ 鉱業、採石業、砂 利採取業 | C6: 鉱業、採石業、砂利採取業 | D6: 製造業その他 | E6: 20人以下
A7: 6 | B7: D 建設業 | C7: 総合工事業 | D7: 製造業その他 | E7: 20人以下
A8: 7 | B8: D 建設業 | C8: 職別工事業（設備工事業を除く） | D8: 製造業その他 | E8: 20人以下
A9: 8 | B9: D 建設業 | C9: 設備工事業 | D9: 製造業その他 | E9: 20人以下
A10: 9 | B10: E 製造業 | C10: 食料品製造業 | D10: 製造業その他 | E10: 20人以下
A11: 10 | B11: E 製造業 | C11: 飲料・たばこ・飼料製造業 | D11: 製造業その他 | E11: 20人以下
A12: 11 | B12: E 製造業 | C12: 繊維工業 | D12: 製造業その他 | E12: 20人以下
A13: 12 | B13: E 製造業 | C13: 木材・木製品製造業（家具を除く） | D13: 製造業その他 | E13: 20人以下
A14: 13 | B14: E 製造業 | C14: 家具・装備品製造業 | D14: 製造業その他 | E14: 20人以下
A15: 14 | B15: E 製造業 | C15: パルプ・紙・紙加工品製造業 | D15: 製造業その他 | E15: 20人以下
A16: 15 | B16: E 製造業 | C16: 印刷・同関連業 | D16: 製造業その他 | E16: 20人以下
A17: 16 | B17: E 製造業 | C17: 化学工業 | D17: 製造業その他 | E17: 20人以下
... A42: 41 | B42: G 情報通信業 | C42: 映像・音声・文字情報制作業 411映像情報制作・配給業 412音声情報制作業415広告制作業 416映像・音声・文字情報制作に付帯するサービス業 | D42: 商業サービス業 | E42: 5人以下
B43: G 情報通信業 | C43: 上記以外 | D43: 製造業その他 | E43: 20人以下
A44: 42 | B44: H 運輸業、郵便業 | C44: 鉄道業 | D44: 製造業その他 | E44: 20人以下
A45: 43 | B45: H 運輸業、郵便業 | C45: 道路旅客運送業 | D45: 製造業その他 | E45: 20人以下
A46: 44 | B46: H 運輸業、郵便業 | C46: 道路貨物運送業 | D46: 製造業その他 | E46: 20人以下
A47: 45 | B47: H 運輸業、郵便業 | C47: 水運業 | D47: 製造業その他 | E47: 20人以下
A48: 46 | B48: H 運輸業、郵便業 | C48: 航空運輸業 | D48: 製造業その他 | E48: 20人以下
A49: 47 | B49: H 運輸業、郵便業 | C49: 倉庫業 | D49: 製造業その他 | E49: 20人以下
A50: 48 | B50: H 運輸業、郵便業 | C50: 運輸に附帯するサービス業 | D50: 製造業その他 | E50: 20人以下
A51: 49 | B51: H 運輸業、郵便業 | C51: 郵便業（信書便事業を含む） | D51: 製造業その他 | E51: 20人以下
A52: 50 | B52: I 卸売業・小売業 | C52: 各種商品卸売業 | D52: 商業サービス業 | E52: 5人以下
A53: 51 | B53: I 卸売業・小売業 | C53: 繊維・衣服等卸売業 | D53: 商業サービス業 | E53: 5人以下
A54: 52 | B54: I 卸売業・小売業 | C54: 飲食料品卸売業 | D54: 商業サービス業 | E54: 5人以下
A55: 53 | B55: I 卸売業・小売業 | C55: 建築材料、鉱物・金属材料等卸売業 | D55: 商業サービス業 | E55: 5人以下
... A96: 92 | B96: R サービス業（他に分類されないもの） | C96: その他の事業サービス業 | D96: 商業サービス業 | E96: 5人以下
A97: 93 | B97: R サービス業（他に分類されないもの） | C97: 政治・経済・文化団体 | D97: 支給対象外
A98: 94 | B98: R サービス業（他に分類されないもの） | C98: 宗教
A99: 95 | B99: R サービス業（他に分類されないもの） | C99: その他のサービス業
A100: 96 | B100: S 公務（他に分類されるものを除く） | C100: 外国公務
A101: 97 | B101: S 公務（他に分類されるものを除く） | C101: 国家公務
A102: 98 | B102: S 公務（他に分類されるものを除く） | C102: 地方公務
A103: 99 | B103: Ｔ 分類不能の産業 | C103: 分類不能の産業

Sheet 商品マスタ
B1: 編集不可
B2: ITツール名 | C2: No. | D2: ITツールNo. | E2: 管理コード | F2: 下限 | G2: 上限 | H2: ITツール名
A3: カラフルボックスコンソーシアム | B3: 貿易クラウド_利用料 | C3: DL06-0000792-001 | E3: 貿易001 | F3: 600000 | G3: 3000000 | H3: 目標管理クラウドcbox_ベーシック
A4: カラフルボックスコンソーシアム | B4: カンリル_利用料 | C4: DL06-0029228-001 | E4: カンリル001 | F4: 32509 | G4: 325091 | H4: 目標管理クラウドcbox_スタンダード
A5: カラフルボックスコンソーシアム | B5: 社長メシ_スタンダードプラン | C5: DL06-0029652-001 | E5: 社長メシ001 | F5: 1500000 | G5: 1500000 | H5: 目標管理クラウドcbox_プレミアム
A6: カラフルボックスコンソーシアム | B6: せきなび_スタンダード | C6: DL06-0002760-001 | E6: seknavi01 | F6: 300000 | G6: 360000 | H6: 目標管理クラウドcbox_ベーシック_初期設定
A7: カラフルボックスコンソーシアム | B7: カンリル_導入・活用コンサルティング | C7: DL07-0001708 | E7: カンリル003 | F7: 20000 | G7: 150000 | H7: 目標管理クラウドcbox_ベーシック_保守・サポート
A8: カラフルボックスコンソーシアム | B8: カンリル_初期設定 | C8: DL07-0001738 | E8: カンリル002 | F8: 50000 | G8: 150000 | H8: 目標管理クラウドcbox_導入・活用コンサルティング
A9: カラフルボックスコンソーシアム | B9: Scale人事評価_スタンダードプラン | C9: DL07-0002412 | E9: Scale001 | F9: 1920 | G9: 12000 | H9: 目標管理クラウドcbox_スタンダード_初期設定
A10: カラフルボックスコンソーシアム | B10: AI Works_保守・サポート | C10: DL07-0001726 | E10: AIWorks005 | F10: 120000 | G10: 600000 | H10: 目標管理クラウドcbox_スタンダード_保守・サポート
A11: カラフルボックスコンソーシアム | B11: AI Works_利用料 | C11: DL06-0001191-001 | E11: AIWorks001 | F11: 120000 | G11: 360000 | H11: 目標管理クラウドcbox_プレミアム_初期設定
A12: カラフルボックスコンソーシアム | B12: カンリル_保守サポート | C12: DL07-0001733 | E12: カンリル004 | F12: 60000 | G12: 125000 | H12: 目標管理クラウドcbox_プレミアム_保守・サポート
A13: カラフルボックスコンソーシアム | B13: freee会計_スタータープラン | C13: DL07-0007357 | E13: freee会計001 | F13: 65760 | G13: 65760 | H13: 貿易クラウド_利用料
A14: カラフルボックスコンソーシアム | B14: Scale人事評価スタンダードプラン_初期設定 | C14: DL07-0020657 | E14: Scale002 | F14: 80000 | G14: 160000 | H14: AI Works_利用料
A15: カラフルボックスコンソーシアム | B15: AI Works_初期設定 | C15: DL07-0003894 | E15: AIWorks003 | F15: 10000 | G15: 200000 | H15: AI Works_利用料_初期設定
A16: カラフルボックスコンソーシアム | B16: PCセキュリティみまもりパック | C16: DL07-0002804 | E16: pcsecurity | H16: AI Works_利用料_保守・サポート
A17: カラフルボックスコンソーシアム | B17: Scale人事評価_導入・活用コンサルティング | C17: DL07-0020659 | E17: Scale003 | F17: 300000 | G17: 900000 | H17: AI Works_導入活用コンサルティング
A18: カラフルボックスコンソーシアム | B18: AI Works_導入活用コンサルティング | C18: DL07-0003887 | E18: AIWorks002 | F18: 100000 | G18: 450000 | H18: LINE公式アカウント_ライトプラン
A19: カラフルボックスコンソーシアム | B19: Scale人事評価スタンダードプラン_保守サポート | C19: DL07-0020660 | E19: Scale004 | F19: 120000 | G19: 480000 | H19: LINE公式アカウント_スタンダードプラン
A20: クラフトバンク | B20: クラフトバンクオフィス プロフェッショナルプラン | C20: DL04-0029552-004 | E20: クラフトバンクオフィス プロフェッショナルプラン | F20: 1080000 | G20: 2160000 | H20: Lステップ_スタートプラン
A21: クラフトバンク | B21: クラフトバンクオフィス エンタープライズプラン | C21: DL04-0029554-004 | E21: クラフトバンクオフィス エンタープライズプラン | F21: 1350000 | G21: 2700000 | H21: Lステップ_スタンダードプラン
A22: クラフトバンク | B22: 導入コンサルティング活用コンサルティング（クラフトバンクオフィス スタンダードプラン） | C22: DL07-0000180 | E22: 導入コンサルティング活用コンサルティング（クラフトバンクオフィス スタンダードプラン） | F22: 600000 | G22: 1205000 | H22: Lステップ_プロプラン
A23: クラフトバンク | B23: 導入コンサルティング（クラフトバンクオフィス プロフェッショナルプラン） | C23: DL07-0000059 | E23: 導入コンサルティング（クラフトバンクオフィス プロフェッショナルプラン） | F23: 800000 | G23: 1600000 | H23: UTAGE_ライトプラン
A24: クラフトバンク | B24: クラフトバンクオフィス スタンダードプラン | C24: DL04-0029553-003 | E24: クラフトバンクオフィス スタンダードプラン | F24: 600000 | G24: 1200000 | H24: UTAGE_スタンダードプラン
A25: クラフトバンク | B25: 導入コンサルティング（クラフトバンクオフィス スタンダードプラン） | C25: DL07-0000025 | E25: 導入コンサルティング（クラフトバンクオフィス スタンダードプラン） | F25: 400000 | G25: 800000 | H25: せきなび_スタンダード
A26: クラフトバンク | B26: 初期設定（クラフトバンクオフィス プロフェッショナルプラン） | C26: DL07-0000070 | E26: 初期設定（クラフトバンクオフィス プロフェッショナルプラン） | F26: 1200000 | G26: 1800000 | H26: CRS人材募集管理システム_ベーシック
A27: クラフトバンク | B27: 初期設定（クラフトバンクオフィス スタンダードプラン） | C27: DL07-0000036 | E27: 初期設定（クラフトバンクオフィス スタンダードプラン） | F27: 600000 | G27: 1200000 | H27: CRS人材募集管理システム_ベーシック_初期導入
A28: クラフトバンク | B28: 導入コンサルティング活用コンサルティング（クラフトバンクオフィス プロフェッショナルプラン | C28: DL07-0001646 | E28: 導入コンサルティング活用コンサルティング（クラフトバンクオフィス プロフェッショナルプラン | F28: 1000000 | G28: 1805000 | H28: CRS人材募集管理システム_ベーシック_保守・サポート
A29: クラフトバンク | B29: 導入コンサルティング活用コンサルティング（プロフェッショナルプラン） | C29: DL07-0004098 | E29: 導入コンサルティング活用コンサルティング（プロフェッショナルプラン） | F29: 1000000 | G29: 1920000
A30: ピスケス | B30: 着信ポップアップCTI | C30: DL06-0034655-001 | E30: PSA003 | F30: 108000 | G30: 120000
A31: ピスケス | B31: LINEコネクト | C31: DL06-0033682-001 | E31: PLINE | F31: 64000 | G31: 80000
A32: ピスケス | B32: ピスケスアポ | C32: DL05-0024072-002 | E32: piscesapo2024 | F32: 408000 | G32: 480000
A33: ピスケス | B33: SMS | C33: DL06-0034634-001 | E33: PKA002 | F33: 64000 | G33: 80000
A34: いろはな | B34: irohana study スモール | C34: DL07-0024780 | E34: study_s | F34: 237600 | G34: 357600
A35: いろはな | B35: irohana visa スモール | C35: DL07-0014825 | E35: visa_s | F35: 357600 | G35: 357600
A36: いろはな | B36: irohana study スタンダード | C36: DL07-0024781 | E36: study_m | F36: 357600 | G36: 477600
A37: いろはな | B37: irohana 導入コンサルティング等 | C37: DL07-0019039 | E37: 導入コンサルティング等 | F37: 200000 | G37: 200000
A38: いろはな | B38: irohana visa ラージ | C38: DL07-0019031 | E38: visa_l | F38: 597600 | G38: 597600
A39: いろはな | B39: irohana visa スモール導入設定等 | C39: DL07-0019034 | E39: 導入設定等_visa_s | F39: 50000 | G39: 150000
A40: いろはな | B40: irohana visa ラージ導入設定等 | C40: DL07-0020470 | E40: 導入設定等_visa_l | F40: 50000 | G40: 150000
... A45: いろはな | B45: irohana study スモール導入設定等 | C45: DL07-0028059 | E45: 導入設定等_study_s | F45: 50000 | G45: 150000

Sheet プルダウン用
B1: 都道府県名
A2: 1月 | B2: 北海道/1075円 | C2: A、農業林業
A3: 2月 | B3: 青森/1029円 | C3: B、漁業
A4: 3月 | B4: 岩手/1031円 | C4: C、鉱業、採石業、砂利採取業
A5: 4月 | B5: 宮城/1038円 | C5: D、建設業
A6: 5月 | B6: 秋田/1031円 | C6: E、製造業
A7: 6月 | B7: 山形/1032円 | C7: F、電気、ガス、熱供給・水道業
A8: 7月 | B8: 福島/1033円 | C8: G、情報通信業
A9: 8月 | B9: 茨城/1074円 | C9: H、運輸業、郵便業
A10: 9月 | B10: 栃木/1068円 | C10: I、卸売業、小売業
A11: 10月 | B11: 群馬/1063円 | C11: J、金融業、保険業
A12: 11月 | B12: 埼玉/1141円 | C12: K、不動産業、物品賃貸業
A13: 12月 | B13: 千葉/1140円 | C13: L、学術研究、専門・技術サービス業
B14: 東京/1226円 | C14: M、宿泊業、飲食サービス業
B15: 神奈川/1225円 | C15: N、生活関連サービス業、娯楽業
B16: 新潟/1050円 | C16: O、教育、学習支援業
B17: 富山/1062円 | C17: P、医療 福祉
B18: 石川/1054円 | C18: Q、複合サービス事業
B19: 福井/1053円 | C19: R、サービス業（他に分類されないもの）
B20: 山梨/1052円 | C20: S、公務（他に分類されるものを除く）
B21: 長野/1061円
B22: 岐阜/1065円
B23: 静岡/1097円
B24: 愛知/1140円
B25: 三重/1087円
B26: 滋賀/1080円
B27: 京都/1122円
B28: 大阪/1177円
B29: 兵庫/1116円
B30: 奈良/1051円
B31: 和歌山/1045円
B32: 鳥取/1030円
... B48: 沖縄/1023円

Sheet 実績報告
B3: 申請時添付資料
B4: FALSE | C4: 請求書 | E4: ・契約年数が記載されている ・ITツールの「単価」とシステムの入力値が一致する
B5: FALSE | C5: 支払証憑 | E5: ・支払いが完了したことを確認できる ・支払金額」「支払日」「支払元」
B6: FALSE | C6: 画面キャプチャ
B7: FALSE | C7: 補助金受取口座
B8: FALSE | C8: 従業員一覧（小規模事業者のみ） | E8: ・申請時の従業員数から変更がないか確認
B9: FALSE | C9: その他資料 ・差額分の請求書など
B10: FALSE | C10: 役務資料
B13: 申請マイページにログイン
B14: 「申請者メニュー」の 【実績報告情報編集】をクリック
B15: 「ITツールの解約」に関する説明動画を確認し、【次へ】を
B18: 請求明細書
B20: ファイル添付
D21: チェック項目
D22: TRUE | E22: 補助事業社名に誤りがない
D23: FALSE | E23: 契約年数が記載されている
D24: FALSE | E24: ITツールの「単価」とシステムの入力値が一致する
D25: FALSE
D26: FALSE
D27: FALSE
D28: FALSE
D29: FALSE
D30: FALSE
D31: FALSE
B34: 『 次へ 』 | C34: をクリック
B36: 支払方法選択
B38: ▪️ 銀行振込 □ クレジットカード
B40: 『 次へ 』 | C40: をクリック
B42: 支払証憑
B44: ファイル添付
B46: 『 次へ 』 | C46: をクリック
B48: その他添付資料
B50: ファイル添付
B52: ファイル添付
B54: 『 次へ 』 | C54: をクリック
B56: ソフトウエア証憑
B58: ファイル添付
B60: 『 次へ 』 | C60: をクリック
B62: ハードウエア（PC•タブレット•プリンター•スキャナー・複合機）導入情報
B64: ハードウェア（PC・タブレット・プリンター・スキャナー・複合機）の導入を行いましたか？ □はい ▪️いいえ
B66: 『 次へ 』 | C66: をクリック | E66: ※「いいえ」にチェック
B68: ハードウエア（POSレジ•モバイルPOSレジ•券売機）導入情報
B70: ハードウェア（POSレジ・モバイルPOSレジ・券売機）の導入を行いましたか？ □ はい ▪️ いいえ
B72: 『 次へ 』 | C72: をクリック | E72: ※「いいえ」にチェック
B74: 口座情報
B76: ファイル添付
B78: 『 次へ 』 | C78: をクリック
B80: 口座情報入力
B82: 通帳の表紙/表紙裏面 | C82: ④補助金受取口座
B84: 金融機関コード
B86: 金融機関名
B88: 支店コード
B90: 支店名
C92: 検索 | E92: ⇨「検索」より
C94: 🔹金融機関名（最初の１文字以上/カタカナ）
C96: 🔹支店コード（半角3桁）
B99: 口座種別
B101: 口座名義（半角カナ）
B103: 口座番号
B106: 『 次へ 』 | C106: をクリック
B108: 補助事業者入力確認
B110: 『 実績報告入力完了』 | C110: をクリック⇨『IT導入支援事業者に引き継がれました』と表示

Sheet 編集用
B5: 北海道 | C5: 1075 | D5: / | E5: =B5&D5&C5&F5 | F5: 円
B6: 青森 | C6: 1029 | D6: / | E6: =B6&D6&C6&F6 | F6: 円
B7: 岩手 | C7: 1031 | D7: / | E7: =B7&D7&C7&F7 | F7: 円
B8: 宮城 | C8: 1038 | D8: / | E8: =B8&D8&C8&F8 | F8: 円
B9: 秋田 | C9: 1031 | D9: / | E9: =B9&D9&C9&F9 | F9: 円
B10: 山形 | C10: 1032 | D10: / | E10: =B10&D10&C10&F10 | F10: 円
B11: 福島 | C11: 1033 | D11: / | E11: =B11&D11&C11&F11 | F11: 円
B12: 茨城 | C12: 1074 | D12: / | E12: =B12&D12&C12&F12 | F12: 円
B13: 栃木 | C13: 1068 | D13: / | E13: =B13&D13&C13&F13 | F13: 円
B14: 群馬 | C14: 1063 | D14: / | E14: =B14&D14&C14&F14 | F14: 円
B15: 埼玉 | C15: 1141 | D15: / | E15: =B15&D15&C15&F15 | F15: 円
B16: 千葉 | C16: 1140 | D16: / | E16: =B16&D16&C16&F16 | F16: 円
... B51: 沖縄 | C51: 1023 | D51: / | E51: =B51&D51&C51&F51 | F51: 円
